membrain/__init__.py
membrain/bibtex.py
membrain/constants.py
membrain/icon.png
membrain/protocols.conf
membrain/protocols/__init__.py
membrain/protocols/protocol_membrain_seg.py
membrain/protocols/protocol_membrain_skeletonize.py
membrain/tests/__init__.py
membrain/tests/test_membrain.py
scipion_em_membrain-3.1.2.dist-info/LICENSE
scipion_em_membrain-3.1.2.dist-info/METADATA
scipion_em_membrain-3.1.2.dist-info/WHEEL
scipion_em_membrain-3.1.2.dist-info/entry_points.txt
scipion_em_membrain-3.1.2.dist-info/top_level.txt
scipion_em_membrain-3.1.2.dist-info/RECORD
