Metadata-Version: 2.1
Name: scipion-em-membrain
Version: 3.1.2
Summary: Plugin to use membrain within the Scipion framework
Author-email: Scipion Team <scipion@cnb.csic.es>
License: GNU General Public License v3 (GPLv3)
Project-URL: Homepage, https://github.com/scipion-em/scipion-em-membrain
Project-URL: Issues, https://github.com/scipion-em/scipion-em-membrain/issues
Keywords: scipion,cryoem,cryoet,imageprocessing,scipion-3.0
Classifier: Development Status :: 4 - Beta
Classifier: License :: OSI Approved :: GNU General Public License v3 (GPLv3)
Classifier: Programming Language :: Python :: 3
Requires-Python: >=3.8
License-File: LICENSE
Requires-Dist: scipion-pyworkflow>=3.11.6
Requires-Dist: scipion-em-tomo>=3.11.3
